{
  "sessions": [
    {
      "id": "workshop-registration",
      "title": "Registration & Breakfast",
      "type": "break",
      "dayId": "workshop-day",
      "timeSlotId": "ws-slot1",
      "description": "Registration and welcome breakfast for workshop participants.",
      "isFullWidth": true
    },
    {
      "id": "workshop-morning-1",
      "title": "Workshop TBA",
      "type": "workshop",
      "dayId": "workshop-day",
      "timeSlotId": "ws-slot2",
      "trackId": "track1",
      "roomId": "room1",
      "description": "Details for this workshop will be announced soon. Stay tuned for updates!",
      "speakerIds": ["speaker-1"],
      "tags": [],
      "level": "all"
    },
    {
      "id": "workshop-morning-2",
      "title": "Workshop TBA",
      "type": "workshop",
      "dayId": "workshop-day",
      "timeSlotId": "ws-slot2",
      "trackId": "track2",
      "roomId": "room2",
      "description": "Details for this workshop will be announced soon. Stay tuned for updates!",
      "speakerIds": ["speaker-1"],
      "tags": [],
      "level": "all"
    },
    {
      "id": "workshop-lunch",
      "title": "Lunch",
      "type": "break",
      "dayId": "workshop-day",
      "timeSlotId": "ws-slot3",
      "description": "Lunch break for workshop participants.",
      "isFullWidth": true
    },
    {
      "id": "workshop-afternoon-1",
      "title": "Workshop TBA",
      "type": "workshop",
      "dayId": "workshop-day",
      "timeSlotId": "ws-slot4",
      "trackId": "track1",
      "roomId": "room1",
      "description": "Details for this workshop will be announced soon. Stay tuned for updates!",
      "speakerIds": ["speaker-1"],
      "tags": [],
      "level": "all"
    },
    {
      "id": "workshop-afternoon-2",
      "title": "Workshop TBA",
      "type": "workshop",
      "dayId": "workshop-day",
      "timeSlotId": "ws-slot4",
      "trackId": "track2",
      "roomId": "room2",
      "description": "Details for this workshop will be announced soon. Stay tuned for updates!",
      "speakerIds": ["speaker-1"],
      "tags": [],
      "level": "all"
    },
    {
      "id": "workshop-networking",
      "title": "Networking",
      "type": "break",
      "dayId": "workshop-day",
      "timeSlotId": "ws-slot5",
      "description": "Networking and informal discussions among workshop participants.",
      "isFullWidth": true
    },
    {
      "id": "conference-registration",
      "title": "Registration & Networking",
      "type": "break",
      "dayId": "conference-day",
      "timeSlotId": "conf-slot1",
      "description": "Welcome to Cloud Native Days Italy 2025! Join us for registration, coffee, and networking with fellow attendees.",
      "isFullWidth": true
    },
    {
      "id": "opening-keynote",
      "title": "🗝️ Opening Keynote",
      "type": "keynote",
      "dayId": "conference-day",
      "timeSlotId": "conf-slot2",
      "trackId": "track1",
      "roomId": "room1",
      "description": "Join us for the opening keynote where we'll explore the future of cloud native technologies and how they are shaping the industry.",
      "speakerIds": ["monica-colangelo","maurizio-argoneto","speaker-1"],
      "isFullWidth": true
    },
    {
      "id": "session-1-track1",
      "title": "Session TBA",
      "type": "talk",
      "dayId": "conference-day",
      "timeSlotId": "conf-slot3",
      "trackId": "track1",
      "roomId": "room1",
      "description": "Details for this session will be announced soon. Stay tuned for updates!",
      "speakerIds": ["speaker-1"],
      "tags": [],
      "level": "all"
    },
    {
      "id": "session-1-track2",
      "title": "Session TBA",
      "type": "talk",
      "dayId": "conference-day",
      "timeSlotId": "conf-slot3",
      "trackId": "track2",
      "roomId": "room2",
      "description": "Details for this session will be announced soon. Stay tuned for updates!",
      "speakerIds": ["speaker-1"],
      "tags": [],
      "level": "all"
    },
    {
      "id": "session-2-track1",
      "title": "Session TBA",
      "type": "talk",
      "dayId": "conference-day",
      "timeSlotId": "conf-slot4",
      "trackId": "track1",
      "roomId": "room1",
      "description": "Details for this session will be announced soon. Stay tuned for updates!",
      "speakerIds": ["speaker-1"],
      "tags": [],
      "level": "all"
    },
    {
      "id": "session-2-track2",
      "title": "Session TBA",
      "type": "talk",
      "dayId": "conference-day",
      "timeSlotId": "conf-slot4",
      "trackId": "track2",
      "roomId": "room2",
      "description": "Details for this session will be announced soon. Stay tuned for updates!",
      "speakerIds": ["speaker-1"],
      "tags": [],
      "level": "all"
    },
    {
      "id": "coffee-break-1",
      "title": "☕ Coffee Break",
      "type": "break",
      "dayId": "conference-day",
      "timeSlotId": "conf-slot5",
      "description": "Refresh with coffee and snacks while networking with other attendees.",
      "isFullWidth": true
    },
    {
      "id": "session-3-track1",
      "title": "Session TBA",
      "type": "talk",
      "dayId": "conference-day",
      "timeSlotId": "conf-slot6",
      "trackId": "track1",
      "roomId": "room1",
      "description": "Details for this session will be announced soon. Stay tuned for updates!",
      "speakerIds": ["speaker-1"],
      "tags": [],
      "level": "all"
    },
    {
      "id": "session-3-track2",
      "title": "Session TBA",
      "type": "talk",
      "dayId": "conference-day",
      "timeSlotId": "conf-slot6",
      "trackId": "track2",
      "roomId": "room2",
      "description": "Details for this session will be announced soon. Stay tuned for updates!",
      "speakerIds": ["speaker-1"],
      "tags": [],
      "level": "all"
    },
    {
      "id": "session-4-track1",
      "title": "Session TBA",
      "type": "talk",
      "dayId": "conference-day",
      "timeSlotId": "conf-slot7",
      "trackId": "track1",
      "roomId": "room1",
      "description": "Details for this session will be announced soon. Stay tuned for updates!",
      "speakerIds": ["speaker-1"],
      "tags": [],
      "level": "all"
    },
    {
      "id": "session-4-track2",
      "title": "Session TBA",
      "type": "talk",
      "dayId": "conference-day",
      "timeSlotId": "conf-slot7",
      "trackId": "track2",
      "roomId": "room2",
      "description": "Details for this session will be announced soon. Stay tuned for updates!",
      "speakerIds": ["speaker-1"],
      "tags": [],
      "level": "all"
    },
    {
      "id": "session-5-track1",
      "title": "Session TBA",
      "type": "talk",
      "dayId": "conference-day",
      "timeSlotId": "conf-slot8",
      "trackId": "track1",
      "roomId": "room1",
      "description": "Details for this session will be announced soon. Stay tuned for updates!",
      "speakerIds": ["speaker-1"],
      "tags": [],
      "level": "all"
    },
    {
      "id": "session-5-track2",
      "title": "Session TBA",
      "type": "talk",
      "dayId": "conference-day",
      "timeSlotId": "conf-slot8",
      "trackId": "track2",
      "roomId": "room2",
      "description": "Details for this session will be announced soon. Stay tuned for updates!",
      "speakerIds": ["speaker-1"],
      "tags": [],
      "level": "all"
    },
    {
      "id": "lunch",
      "title": "🍽️ Lunch Break",
      "type": "break",
      "dayId": "conference-day",
      "timeSlotId": "conf-slot9",
      "description": "Enjoy a delicious lunch and network with fellow attendees.",
      "isFullWidth": true
    },
    {
      "id": "session-6-track1",
      "title": "Session TBA",
      "type": "talk",
      "dayId": "conference-day",
      "timeSlotId": "conf-slot10",
      "trackId": "track1",
      "roomId": "room1",
      "description": "Details for this session will be announced soon. Stay tuned for updates!",
      "speakerIds": ["speaker-1"],
      "tags": [],
      "level": "all"
    },
    {
      "id": "session-6-track2",
      "title": "Session TBA",
      "type": "talk",
      "dayId": "conference-day",
      "timeSlotId": "conf-slot10",
      "trackId": "track2",
      "roomId": "room2",
      "description": "Details for this session will be announced soon. Stay tuned for updates!",
      "speakerIds": ["speaker-1"],
      "tags": [],
      "level": "all"
    },
    {
      "id": "session-7-track1",
      "title": "Session TBA",
      "type": "talk",
      "dayId": "conference-day",
      "timeSlotId": "conf-slot11",
      "trackId": "track1",
      "roomId": "room1",
      "description": "Details for this session will be announced soon. Stay tuned for updates!",
      "speakerIds": ["speaker-1"],
      "tags": [],
      "level": "all"
    },
    {
      "id": "session-7-track2",
      "title": "Session TBA",
      "type": "talk",
      "dayId": "conference-day",
      "timeSlotId": "conf-slot11",
      "trackId": "track2",
      "roomId": "room2",
      "description": "Details for this session will be announced soon. Stay tuned for updates!",
      "speakerIds": ["speaker-1"],
      "tags": [],
      "level": "all"
    },
    {
      "id": "coffee-break-2",
      "title": "☕ Coffee Break",
      "type": "break",
      "dayId": "conference-day",
      "timeSlotId": "conf-slot12",
      "description": "Refresh with coffee and snacks while networking with other attendees.",
      "isFullWidth": true
    },
    {
      "id": "session-8-track1",
      "title": "Session TBA",
      "type": "talk",
      "dayId": "conference-day",
      "timeSlotId": "conf-slot13",
      "trackId": "track1",
      "roomId": "room1",
      "description": "Details for this session will be announced soon. Stay tuned for updates!",
      "speakerIds": ["speaker-1"],
      "tags": [],
      "level": "all"
    },
    {
      "id": "session-8-track2",
      "title": "Session TBA",
      "type": "talk",
      "dayId": "conference-day",
      "timeSlotId": "conf-slot13",
      "trackId": "track2",
      "roomId": "room2",
      "description": "Details for this session will be announced soon. Stay tuned for updates!",
      "speakerIds": ["speaker-1"],
      "tags": [],
      "level": "all"
    },
    {
      "id": "session-9-track1",
      "title": "Session TBA",
      "type": "talk",
      "dayId": "conference-day",
      "timeSlotId": "conf-slot14",
      "trackId": "track1",
      "roomId": "room1",
      "description": "Details for this session will be announced soon. Stay tuned for updates!",
      "speakerIds": ["speaker-1"],
      "tags": [],
      "level": "all"
    },
    {
      "id": "session-9-track2",
      "title": "Session TBA",
      "type": "talk",
      "dayId": "conference-day",
      "timeSlotId": "conf-slot14",
      "trackId": "track2",
      "roomId": "room2",
      "description": "Details for this session will be announced soon. Stay tuned for updates!",
      "speakerIds": ["speaker-1"],
      "tags": [],
      "level": "all"
    },
    {
      "id": "session-10-track1",
      "title": "Session TBA",
      "type": "talk",
      "dayId": "conference-day",
      "timeSlotId": "conf-slot15",
      "trackId": "track1",
      "roomId": "room1",
      "description": "Details for this session will be announced soon. Stay tuned for updates!",
      "speakerIds": ["speaker-1"],
      "tags": [],
      "level": "all"
    },
    {
      "id": "session-10-track2",
      "title": "Session TBA",
      "type": "talk",
      "dayId": "conference-day",
      "timeSlotId": "conf-slot15",
      "trackId": "track2",
      "roomId": "room2",
      "description": "Details for this session will be announced soon. Stay tuned for updates!",
      "speakerIds": ["speaker-1"],
      "tags": [],
      "level": "all"
    },
    {
      "id": "closing-remarks",
      "title": "🗣️ Closing Remarks",
      "type": "keynote",
      "dayId": "conference-day",
      "timeSlotId": "conf-slot16",
      "trackId": "track1",
      "roomId": "room1",
      "description": "Join us for the closing remarks summarizing the key takeaways from Cloud Native Days Italy 2025.",
      "speakerIds": ["speaker-1"],
      "isFullWidth": true
    },
    {
      "id": "aperitivo-networking",
      "title": "🥂 Aperitivo & Networking",
      "type": "break",
      "dayId": "conference-day",
      "timeSlotId": "conf-slot17",
      "description": "Join us for aperitivo and networking. A perfect opportunity to connect with speakers and fellow attendees.",
      "isFullWidth": true
    }
  ]
}
